jupyterlab_autosave_on_focus_change/__init__.py
jupyterlab_autosave_on_focus_change/_version.py
jupyterlab_autosave_on_focus_change-0.4.1.data/data/share/jupyter/labextensions/jupyterlab_autosave_on_focus_change/package.json
jupyterlab_autosave_on_focus_change-0.4.1.data/data/share/jupyter/labextensions/jupyterlab_autosave_on_focus_change/schemas/jupyterlab_autosave_on_focus_change/package.json.orig
jupyterlab_autosave_on_focus_change-0.4.1.data/data/share/jupyter/labextensions/jupyterlab_autosave_on_focus_change/schemas/jupyterlab_autosave_on_focus_change/plugin.json
jupyterlab_autosave_on_focus_change-0.4.1.data/data/share/jupyter/labextensions/jupyterlab_autosave_on_focus_change/schemas/jupyterlab_autosave_on_focus_change/settings.json
jupyterlab_autosave_on_focus_change-0.4.1.data/data/share/jupyter/labextensions/jupyterlab_autosave_on_focus_change/static/25.e4c154e7b7e64e32bd0e.js
jupyterlab_autosave_on_focus_change-0.4.1.data/data/share/jupyter/labextensions/jupyterlab_autosave_on_focus_change/static/556.a960f518ef16b9a9e33b.js
jupyterlab_autosave_on_focus_change-0.4.1.data/data/share/jupyter/labextensions/jupyterlab_autosave_on_focus_change/static/673.33e0289dbee089055fc1.js
jupyterlab_autosave_on_focus_change-0.4.1.data/data/share/jupyter/labextensions/jupyterlab_autosave_on_focus_change/static/remoteEntry.44e74e19e5b8f1a0b7de.js
jupyterlab_autosave_on_focus_change-0.4.1.data/data/share/jupyter/labextensions/jupyterlab_autosave_on_focus_change/static/style.js
jupyterlab_autosave_on_focus_change-0.4.1.data/data/share/jupyter/labextensions/jupyterlab_autosave_on_focus_change/static/third-party-licenses.json
jupyterlab_autosave_on_focus_change-0.4.1.data/data/share/jupyter/labextensions/jupyterlab_autosave_on_focus_change/install.json
jupyterlab_autosave_on_focus_change-0.4.1.dist-info/METADATA
jupyterlab_autosave_on_focus_change-0.4.1.dist-info/WHEEL
jupyterlab_autosave_on_focus_change-0.4.1.dist-info/licenses/LICENSE
jupyterlab_autosave_on_focus_change-0.4.1.dist-info/RECORD
