Metadata-Version: 2.3
Name: jupyterlab_autosave_on_focus_change
Version: 0.4.1
Summary: Jupyterlab extension to autosave files on focus change
Project-URL: Homepage, https://github.com/s-weigand/jupyterlab_autosave_on_focus_change
Project-URL: Bug Tracker, https://github.com/s-weigand/jupyterlab_autosave_on_focus_change/issues
Project-URL: Repository, https://github.com/s-weigand/jupyterlab_autosave_on_focus_change.git
Author-email: Sebastian Weigand <s.weigand.phy@gmail.com>
License: BSD 3-Clause License
License-File: LICENSE
Keywords: jupyter,jupyterlab,jupyterlab-extension
Classifier: Framework :: Jupyter
Classifier: Framework :: Jupyter :: JupyterLab
Classifier: Framework :: Jupyter :: JupyterLab :: 4
Classifier: Framework :: Jupyter :: JupyterLab :: Extensions
Classifier: Framework :: Jupyter :: JupyterLab :: Extensions :: Prebuilt
Classifier: License :: OSI Approved :: BSD License
Classifier: Programming Language :: Python
Classifier: Programming Language :: Python :: 3
Classifier: Programming Language :: Python :: 3.9
Classifier: Programming Language :: Python :: 3.10
Classifier: Programming Language :: Python :: 3.11
Classifier: Programming Language :: Python :: 3.12
Requires-Python: >=3.9
